[
  {
    "kernelSource": {
      "device": "Spacewar",
      "vendor": "nothing",
      "name": "bimasakti-sukisu",
      "defconfig": "vendor/lahaina-qgki_defconfig",
      "repo": "https://github.com/William24hmar/kernel_nothing_sm7325",
      "branch": "lineage-22.2"
    },
    "output_image": "Image.gz-dtb",
    "use_python2": true,
    "kp": {"use": false},
    "kernelsu": {"enable": false},  // Disable SukiSU for first test
    "toolchains": [],
    "ccache": true,
    "params": {
      "ARCH": "arm64",
      "CC": "aarch64-linux-gnu-gcc",
      "externalCommand": {
        "CROSS_COMPILE": "aarch64-linux-gnu-",
        "CROSS_COMPILE_ARM32": "arm-linux-gnueabi-"
      }
    },
    "image": {"use": false},
    "AnyKernel3": {"use": false}
  }
]
